{"organizations": [], "uuid": "8e349b7bf0b2c4c0eb86193ae47dca410534db9d", "thread": {"site_full": "www.slideshare.net", "main_image": "http://cdn.slidesharecdn.com/ss_thumbnails/goodtechcolaboramerica-161119170754-thumbnail-4.jpg?cb=1479575330", "site_section": "http://www.slideshare.net/rss/latest", "section_title": "Recently Uploaded Slideshows", "url": "http://www.slideshare.net/btincq/good-tech-can-technology-tackle-wicked-problems", "country": "US", "domain_rank": 160, "title": "Good Tech: Can Technology Tackle Wicked Problems?", "performance_score": 0, "site": "slideshare.net", "participants_count": 1, "title_full": "Good Tech: Can Technology Tackle Wicked Problems?", "spam_score": 0.0, "site_type": "news", "published": "2016-11-20T00:07:00.000+02:00", "replies_count": 0, "uuid": "8e349b7bf0b2c4c0eb86193ae47dca410534db9d"}, "author": "btincq@slideshare.net(btincq)", "url": "http://www.slideshare.net/btincq/good-tech-can-technology-tackle-wicked-problems", "ord_in_thread": 0, "title": "Good Tech: Can Technology Tackle Wicked Problems?", "locations": [], "entities": {"persons": [], "locations": [{"name": "rio de janeiro", "sentiment": "none"}], "organizations": []}, "highlightText": "", "language": "english", "persons": [], "text": "Show related SlideShares at end WordPress Shortcode Good Tech: Can Technology Tackle Wicked Problems? 44 views \nPublished on Nov 19, 2016 As digital transformation and tech progress accelerates, it has never been easier to leveraging tech to solve complexe problems: from digital circular fabrication, to low-cost open source prosthetics, drone-based industrial reforestation or artificial intelligence to tackle unemployment. In this keynote, I presented a few areas where tech could help us build a better world, while suggesting some design principles to ensure long-term sustainability, mission alignment, fair value distribution. Slides from a speech I gave at ColaborAmerica 2016 in Rio De Janeiro, on November 18th, 2016. ...", "external_links": [], "published": "2016-11-20T00:07:00.000+02:00", "crawled": "2016-11-19T19:25:37.093+02:00", "highlightTitle": "", "social": {"gplus": {"shares": 0}, "pinterest": {"shares": 0}, "vk": {"shares": 0}, "linkedin": {"shares": 0}, "facebook": {"likes": 0, "shares": 0, "comments": 0}, "stumbledupon": {"shares": 0}}}